hip_wrapper.cpython-36m-x86_64-linux-gnu.so
hippy/__init__.py
hippy/operations.py
hippy/readers.py
hippy/writers.py
hipppy-0.1.0.dist-info/METADATA
hipppy-0.1.0.dist-info/WHEEL
hipppy-0.1.0.dist-info/top_level.txt
hipppy-0.1.0.dist-info/RECORD
