Metadata-Version: 2.1
Name: hipppy
Version: 0.1.0
Summary: A Python interface to Hip which is a package for manipulating
Home-page: http://www.cerfacs.fr/avbp7x/hip.php
Author: Jens-Dominik Mueller, CERFACS
Author-email: j.mueller@qmul.ac.uk, gabriel.staffelbach@cerfacs.fr, erraiya@cerfacs.fr
License: CeCILL-B Free Software License Agreement (CECILL-B)
Platform: UNKNOWN
Classifier: Development Status :: 4 - Beta
Classifier: Programming Language :: Python :: 3.6
Classifier: Programming Language :: Python :: 3.7
Classifier: Programming Language :: Python :: 3.8
Classifier: Programming Language :: Python :: 3.9
Classifier: Topic :: Scientific/Engineering :: Physics
Requires-Python: >=3.6.0
